base_x_fast-0.2.1.dist-info/METADATA
base_x_fast-0.2.1.dist-info/WHEEL
base_x_fast/__init__.py
base_x_fast/base_x_fast.cpython-39-darwin.so
base_x_fast-0.2.1.dist-info/RECORD
